epic/lib.py
epic_lib-0.0.1.dist-info/licenses/LICENSE.txt
epic_lib-0.0.1.dist-info/METADATA
epic_lib-0.0.1.dist-info/WHEEL
epic_lib-0.0.1.dist-info/top_level.txt
epic_lib-0.0.1.dist-info/RECORD
