Metadata-Version: 2.4
Name: epic-lib
Version: 0.0.1
Summary: A library for wrapping models for deployment
License-Expression: BSD-3-Clause
Classifier: Programming Language :: Python :: 3
Requires-Python: >=3.10
License-File: LICENSE.txt
Dynamic: license-file
